metacar/__init__.py
metacar/geometry.py
metacar/models.py
metacar/sceneapi.py
metacar/sockets.py
metacar-0.4.0.dist-info/METADATA
metacar-0.4.0.dist-info/WHEEL
metacar-0.4.0.dist-info/licenses/LICENSE
metacar-0.4.0.dist-info/RECORD
