Metadata-Version: 2.4
Name: metacar
Version: 0.4.0
Summary: 智能网联平台API
Project-URL: Homepage, https://github.com/YDL-Simulation/autodrive_api_python
Project-URL: Issues, https://github.com/YDL-Simulation/autodrive_api_python/issues
Author-email: YDL-Simulation <connie.ma@i-mylab.com>
License-Expression: MIT
License-File: LICENSE
Classifier: Operating System :: OS Independent
Classifier: Programming Language :: Python :: 3
Requires-Python: >=3.10
Requires-Dist: numpy>=2.0.0
Requires-Dist: opencv-python>=4.5.0
Requires-Dist: pydantic>=2.0.0
